[
  {
    "id": 17,
    "nomor": 1,
    "tipe": "reading",
    "petunjuk": "[1–2] 다음 그림을 보고 맞는 단어나 문장을 고르십시오.",
    "soal": "그림",
    "opsi": [
      "광선이다.",
      "천막이다.",
      "차광선이다.",
      "채광장이다."
    ],
    "kunci": "2"
  },
  {
    "id": 17,
    "nomor": 2,
    "tipe": "reading",
    "petunjuk": "[1–2] 다음 그림을 보고 맞는 단어나 문장을 고르십시오.",
    "soal": "그림",
    "opsi": [
      "수질을 재고 있다.",
      "수면을 확인하고 있다.",
      "폐수을 정화하고 있다.",
      "폐수로 강이 오염되어 있다."
    ],
    "kunci": "1"
  },
  {
    "id": 17,
    "nomor": 3,
    "tipe": "reading",
    "petunjuk": "[3–4] 다음 단어와 관계있는 것은 고르십시오.",
    "soal": "고추, 오이, 호박",
    "opsi": [
      "쓰다.",
      "캐다.",
      "따다.",
      "뽑다."
    ],
    "kunci": "3"
  },
  {
    "id": 17,
    "nomor": 4,
    "tipe": "reading",
    "petunjuk": "[3–4] 다음 단어의 비슷말은 무엇입니까?",
    "soal": "인근",
    "opsi": [
      "근거.",
      "주변.",
      "주먹.",
      "근육."
    ],
    "kunci": "2"
  },
  {
    "id": 17,
    "nomor": 5,
    "tipe": "reading",
    "petunjuk": "[5–8] 빈칸에 들아갈 가장 알맞은 것을 고르십시오.",
    "soal": "__________________ 2012년에 행정 업무를 효율적으로 수행하기 위해 만들어진 행정중심복합도시로, 교육부, 고용노 동부 등 대부분의 정부 부처가 위치해 있다.",
    "opsi": [
      "서울 특별시",
      "부산 광역시",
      "인천광역시",
      "세종 특별자치시"
    ],
    "kunci": "4"
  },
  {
    "id": 17,
    "nomor": 6,
    "tipe": "reading",
    "petunjuk": "[5–8] 빈칸에 들아갈 가장 알맞은 것을 고르십시오.",
    "soal": "한국인들은 방이나 마루의 바닥에 __________ 식사를 하거나 휴식을 취하는 좌식 문화를 가지고 있다.",
    "opsi": [
      "앉고",
      "앉아서",
      "앉으면",
      "앉거나"
    ],
    "kunci": "2"
  },
  {
    "id": 17,
    "nomor": 7,
    "tipe": "reading",
    "petunjuk": "[5–8] 빈칸에 들아갈 가장 알맞은 것을 고르십시오.",
    "soal": "다음주에 친구 집들이 때 어떤 선물을 __________ 아직 결정하지 못했다.",
    "opsi": [
      "줄지",
      "준지",
      "준 지",
      "주는지"
    ],
    "kunci": "1"
  },
  {
    "id": 17,
    "nomor": 8,
    "tipe": "reading",
    "petunjuk": "[5–8] 빈칸에 들아갈 가장 알맞은 것을 고르십시오.",
    "soal": "무슨 일이 __________________ 시험날까지는 열심히 공부해야 한다.",
    "opsi": [
      "있아야",
      "없어야",
      "있더라도",
      "없더라도"
    ],
    "kunci": "3"
  }
]